mysql_editor/__main__.py
mysql_editor/add_database.py
mysql_editor/backend.py
mysql_editor/files.py
mysql_editor/query.py
mysql_editor/session.py
mysql_editor/table_data_view.py
mysql_editor/table_structure_view.py
mysql_editor/window.py
mysql_editor_python-2024.6.24.1.dist-info/LICENSE
mysql_editor_python-2024.6.24.1.dist-info/METADATA
mysql_editor_python-2024.6.24.1.dist-info/WHEEL
mysql_editor_python-2024.6.24.1.dist-info/entry_points.txt
mysql_editor_python-2024.6.24.1.dist-info/top_level.txt
mysql_editor_python-2024.6.24.1.dist-info/RECORD
