Metadata-Version: 2.1
Name: mysql_editor_python
Version: 2024.6.24.1
Summary: A MySQL Editor
Project-URL: Homepage, https://github.com/PandaRules/MySQL-Editor-Python
Project-URL: Issues, https://github.com/PandaRules/MySQL-Editor-Python/issues
Project-URL: Changelog, https://github.com/PandaRules/MySQL-Editor-Python/blob/main/CHANGELOG.md
Classifier: Programming Language :: Python :: 3
Classifier: License :: OSI Approved :: MIT License
Classifier: Operating System :: OS Independent
Requires-Python: >=3.8
License-File: LICENSE
Requires-Dist: pyside6 >=6.5.3
Requires-Dist: mysql-connector-python >=8.0.31
